{
	"info": {
		"_postman_id": "9d19d527-01c9-4a2f-ba52-21b846acc4ce",
		"name": "Week4 API",
		"schema": "https://schema.getpostman.com/json/collection/v2.1.0/collection.json",
		"_exporter_id": "49879747",
		"_collection_link": "https://shobhitr-hestabit-5904314.postman.co/workspace/Shobhit-Raj's-Workspace~f3c0a8d1-eded-4a0e-82f9-a4940cf733ac/collection/49879747-9d19d527-01c9-4a2f-ba52-21b846acc4ce?action=share&source=collection_link&creator=49879747"
	},
	"item": [
		{
			"name": "Product",
			"item": [
				{
					"name": "Create Product",
					"request": {
						"method": "GET",
						"header": []
					},
					"response": []
				},
				{
					"name": "All Product",
					"request": {
						"method": "GET",
						"header": []
					},
					"response": []
				},
				{
					"name": "Product by Id",
					"request": {
						"method": "GET",
						"header": []
					},
					"response": []
				},
				{
					"name": "Update product",
					"request": {
						"method": "GET",
						"header": []
					},
					"response": []
				},
				{
					"name": "Delete Product",
					"request": {
						"method": "GET",
						"header": []
					},
					"response": []
				}
			]
		},
		{
			"name": "User",
			"item": [
				{
					"name": "Create user",
					"request": {
						"method": "GET",
						"header": []
					},
					"response": []
				},
				{
					"name": "All users",
					"request": {
						"method": "GET",
						"header": []
					},
					"response": []
				},
				{
					"name": "User By Id",
					"request": {
						"method": "GET",
						"header": []
					},
					"response": []
				},
				{
					"name": "Update User",
					"request": {
						"method": "GET",
						"header": []
					},
					"response": []
				},
				{
					"name": "New Request",
					"request": {
						"method": "GET",
						"header": []
					},
					"response": []
				}
			]
		},
		{
			"name": "Health",
			"item": [
				{
					"name": "Server Health",
					"request": {
						"method": "GET",
						"header": []
					},
					"response": []
				}
			]
		}
	],
	"event": [
		{
			"listen": "prerequest",
			"script": {
				"type": "text/javascript",
				"packages": {},
				"requests": {},
				"exec": [
					""
				]
			}
		},
		{
			"listen": "test",
			"script": {
				"type": "text/javascript",
				"packages": {},
				"requests": {},
				"exec": [
					""
				]
			}
		}
	],
	"variable": [
		{
			"key": "BASE_URL",
			"value": ""
		}
	]
}